ssfm/__init__.py
ssfm/files.py
ssfm/image_segmentation.py
ssfm/instance_registration.py
ssfm/memory_calculator.py
ssfm/mesh_sampler.py
ssfm/object_registration.py
ssfm/object_registration_old.py
ssfm/post_processing.py
ssfm/probabilistic_projection.py
ssfm/workflow.py
semantic_SfM-0.0.5.dist-info/METADATA
semantic_SfM-0.0.5.dist-info/WHEEL
semantic_SfM-0.0.5.dist-info/top_level.txt
semantic_SfM-0.0.5.dist-info/RECORD
