Metadata-Version: 2.1
Name: semantic-SfM
Version: 0.0.5
Summary: instance segmentation on SfM point clouds
Home-page: https://github.com/ZhiangChen/semantic_SfM
Author: Zhiang Chen
Author-email: zhiang.chen@caltech.edu
License: UNKNOWN
Platform: UNKNOWN
Classifier: Development Status :: 3 - Alpha
Classifier: Intended Audience :: Developers
Classifier: Programming Language :: Python :: 3
Classifier: Programming Language :: Python :: 3.6
Classifier: Programming Language :: Python :: 3.7
Classifier: Programming Language :: Python :: 3.8
Classifier: License :: OSI Approved :: Apache Software License
Classifier: Operating System :: OS Independent
Requires-Python: >=3.6
Requires-Dist: laspy (>=2.1.2)
Requires-Dist: numpy (>=1.19.5)
Requires-Dist: matplotlib (>=3.0.3)
Requires-Dist: opencv-python (>=4.8.1)
Requires-Dist: scipy (>=1.5.4)
Requires-Dist: numba (>=0.53.1)
Requires-Dist: logging (>=0.5.1)
Requires-Dist: prettytable (>=2.5.0)
